a2od/__init__.py
a2od-0.0.5.dist-info/LICENSE
a2od-0.0.5.dist-info/METADATA
a2od-0.0.5.dist-info/WHEEL
a2od-0.0.5.dist-info/entry_points.txt
a2od-0.0.5.dist-info/top_level.txt
a2od-0.0.5.dist-info/RECORD
