Metadata-Version: 2.1
Name: a2od
Version: 0.0.5
Summary: Convert Anki style flashcards to Emacs org-drill format
Home-page: https://github.com/yfe404/anki2orgdrill
Author: Yann Feunteun
Author-email: yann.feunteun@protonmail.com
License: UNKNOWN
Platform: UNKNOWN
Classifier: Programming Language :: Python :: 3
Classifier: License :: OSI Approved :: MIT License
Classifier: Operating System :: OS Independent
Requires-Python: >=3.6
Requires-Dist: click
